bin/extract-id.py
ckanext/resource_type_validation/__init__.py
ckanext/resource_type_validation/config_declaration.yaml
ckanext/resource_type_validation/plugin.py
ckanext/resource_type_validation/resource_type_validation.py
ckanext/resource_type_validation/test_mime_type_validation.py
ckanext/resource_type_validation/templates/admin/config.html
ckanext_resource_type_validation-1.0.11.dist-info/licenses/LICENSE
test/features/environment.py
test/features/steps/steps.py
ckanext_resource_type_validation-1.0.11.dist-info/METADATA
ckanext_resource_type_validation-1.0.11.dist-info/WHEEL
ckanext_resource_type_validation-1.0.11.dist-info/entry_points.txt
ckanext_resource_type_validation-1.0.11.dist-info/top_level.txt
ckanext_resource_type_validation-1.0.11.dist-info/RECORD
