Metadata-Version: 2.4
Name: ckanext-resource-type-validation
Version: 1.0.11
Summary: Apply stricter validation to CKAN resource formats
Author-email: ThrawnCA <carl.antuar@smartservice.qld.gov.au>, Queensland Online <qol.development@smartservice.qld.gov.au>, "William Dutton (duttonw)" <william.dutton@qld.gov.au>
Maintainer-email: ThrawnCA <carl.antuar@smartservice.qld.gov.au>, Queensland Online <qol.development@smartservice.qld.gov.au>, "William Dutton (duttonw)" <william.dutton@qld.gov.au>
License: AGPL
Project-URL: Homepage, https://github.com/qld-gov-au/ckanext-resource-type-validation
Keywords: CKAN,extension,validation
Classifier: Development Status :: 5 - Production/Stable
Classifier: License :: OSI Approved :: GNU Affero General Public License v3 or later (AGPLv3+)
Classifier: Programming Language :: Python :: 3.9
Classifier: Programming Language :: Python :: 3.10
License-File: LICENSE
Requires-Dist: typing_extensions
Provides-Extra: test
Requires-Dist: pytest-factoryboy; extra == "test"
Dynamic: license-file
